gps_api/__init__.py
gps_api/cli.py
gps_api/gps_api.py
gps_api/position.py
gps_api-0.1.6.dist-info/AUTHORS.rst
gps_api-0.1.6.dist-info/LICENSE
gps_api-0.1.6.dist-info/METADATA
gps_api-0.1.6.dist-info/WHEEL
gps_api-0.1.6.dist-info/entry_points.txt
gps_api-0.1.6.dist-info/top_level.txt
gps_api-0.1.6.dist-info/RECORD
