Metadata-Version: 2.1
Name: gps-api
Version: 0.1.6
Summary: University of Cape Town EEE3097S 2020 Design Project, API for GPS module
Home-page: https://github.com/jialong-w/gps_api
Author: Jialong Weng, Veronique Reagon
Author-email: wngjia001@myuct.ac.za, rgnver001@myuct.ac.za
License: MIT license
Keywords: gps_api
Platform: UNKNOWN
Classifier: Development Status :: 2 - Pre-Alpha
Classifier: Intended Audience :: Developers
Classifier: License :: OSI Approved :: MIT License
Classifier: Natural Language :: English
Classifier: Programming Language :: Python :: 3
Classifier: Programming Language :: Python :: 3.6
Classifier: Programming Language :: Python :: 3.7
Classifier: Programming Language :: Python :: 3.8
Requires-Python: >=3.6
Requires-Dist: Click (>=7.0)
